README.txt
setup.py
package1/index.py
wenyali_test.egg-info/PKG-INFO
wenyali_test.egg-info/SOURCES.txt
wenyali_test.egg-info/dependency_links.txt
wenyali_test.egg-info/entry_points.txt
wenyali_test.egg-info/top_level.txt
wenyali_test.egg-info/zip-safe